{
  "changes" : [ {
    "targetGroup" : "23П-4",
    "isAbsolute" : true,
    "changesDate" : 1696230000000,
    "changedLessons" : [ {
      "number" : 3,
      "name" : "нет",
      "teacher" : "",
      "place" : "",
      "isChanged" : true
    } ]
  }, {
    "targetGroup" : "23П-5",
    "isAbsolute" : true,
    "changesDate" : 1696230000000,
    "changedLessons" : [ {
      "number" : 1,
      "name" : "История",
      "teacher" : "Каримова И.Р.",
      "place" : "336",
      "isChanged" : true
    } ]
  }, {
    "targetGroup" : "22П-1",
    "isAbsolute" : true,
    "changesDate" : 1696230000000,
    "changedLessons" : [ {
      "number" : 4,
      "name" : "ОАиП",
      "teacher" : "Каримова Р.Ф.",
      "place" : "233",
      "isChanged" : true
    } ]
  }, {
    "targetGroup" : "22П-2",
    "isAbsolute" : true,
    "changesDate" : 1696230000000,
    "changedLessons" : [ {
      "number" : 0,
      "name" : "ОСиС",
      "teacher" : "Лихарев И.А.",
      "place" : "001в",
      "isChanged" : true
    } ]
  }, {
    "targetGroup" : "22П-3",
    "isAbsolute" : true,
    "changesDate" : 1696230000000,
    "changedLessons" : [ {
      "number" : 3,
      "name" : "Ин яз",
      "teacher" : "Пустовалова Э.У.",
      "place" : "331",
      "isChanged" : true
    } ]
  }, {
    "targetGroup" : "22П-4",
    "isAbsolute" : true,
    "changesDate" : 1696230000000,
    "changedLessons" : [ {
      "number" : 3,
      "name" : "ОСиС",
      "teacher" : "Лихарев И.А.",
      "place" : "001в",
      "isChanged" : true
    }, {
      "number" : 4,
      "name" : "ЭВМ",
      "teacher" : "Голуб И.А.",
      "place" : "318",
      "isChanged" : true
    }, {
      "number" : 5,
      "name" : "Физ-ра",
      "teacher" : "Гильманов Р.А.",
      "place" : "",
      "isChanged" : true
    } ]
  }, {
    "targetGroup" : "22БД-1",
    "isAbsolute" : true,
    "changesDate" : 1696230000000,
    "changedLessons" : [ {
      "number" : 2,
      "name" : "нет",
      "teacher" : "",
      "place" : "",
      "isChanged" : true
    }, {
      "number" : 6,
      "name" : "ОПБД",
      "teacher" : "Стюкова Я.Д.",
      "place" : "217",
      "isChanged" : true
    } ]
  }, {
    "targetGroup" : "22ВЕБ-1",
    "isAbsolute" : true,
    "changesDate" : 1696230000000,
    "changedLessons" : [ {
      "number" : 1,
      "name" : "ОСиС",
      "teacher" : "Лихарев И.А.",
      "place" : "001в",
      "isChanged" : true
    }, {
      "number" : 2,
      "name" : "ОСиС",
      "teacher" : "Лихарев И.А.",
      "place" : "001в",
      "isChanged" : true
    } ]
  }, {
    "targetGroup" : "22ВЕБ-2",
    "isAbsolute" : true,
    "changesDate" : 1696230000000,
    "changedLessons" : [ {
      "number" : 1,
      "name" : "нет",
      "teacher" : "",
      "place" : "",
      "isChanged" : true
    }, {
      "number" : 5,
      "name" : "Граф дизайн",
      "teacher" : "Жданова Г.А.",
      "place" : "7",
      "isChanged" : true
    } ]
  }, {
    "targetGroup" : "22ИС-1",
    "isAbsolute" : true,
    "changesDate" : 1696230000000,
    "changedLessons" : [ {
      "number" : 2,
      "name" : "ЭВМ",
      "teacher" : "Голуб И.А.",
      "place" : "318",
      "isChanged" : true
    } ]
  }, {
    "targetGroup" : "21ИС-1",
    "isAbsolute" : true,
    "changesDate" : 1696230000000,
    "changedLessons" : [ {
      "number" : 3,
      "name" : "ПП.05.01",
      "teacher" : "Уразаева А.А.",
      "place" : "227",
      "isChanged" : true
    }, {
      "number" : 4,
      "name" : "ПП.05.01",
      "teacher" : "Уразаева А.А.",
      "place" : "227",
      "isChanged" : true
    } ]
  }, {
    "targetGroup" : "20ИС-1",
    "isAbsolute" : true,
    "changesDate" : 1696230000000,
    "changedLessons" : [ {
      "number" : 3,
      "name" : "Спецкурс",
      "teacher" : "Набиева Л.Р.",
      "place" : "232",
      "isChanged" : true
    }, {
      "number" : 4,
      "name" : "Спецкурс",
      "teacher" : "Набиева Л.Р.",
      "place" : "232",
      "isChanged" : true
    }, {
      "number" : 5,
      "name" : "ПП.07.01",
      "teacher" : "Уразаева А.А.",
      "place" : "227",
      "isChanged" : true
    }, {
      "number" : 6,
      "name" : "ПП.07.01",
      "teacher" : "Уразаева А.А.",
      "place" : "227",
      "isChanged" : true
    } ]
  }, {
    "targetGroup" : "23СА-3",
    "isAbsolute" : true,
    "changesDate" : 1696230000000,
    "changedLessons" : [ {
      "number" : 5,
      "name" : "Физика",
      "teacher" : "Кашапов В.В.",
      "place" : "14",
      "isChanged" : true
    } ]
  }, {
    "targetGroup" : "21УКСК-1",
    "isAbsolute" : true,
    "changesDate" : 1696230000000,
    "changedLessons" : [ {
      "number" : 4,
      "name" : "МПЦ",
      "teacher" : "Лихарев И.А.",
      "place" : "001в",
      "isChanged" : true
    }, {
      "number" : 5,
      "name" : "МПЦ",
      "teacher" : "Лихарев И.А.",
      "place" : "001в",
      "isChanged" : true
    }, {
      "number" : 6,
      "name" : "МПЦ",
      "teacher" : "Лихарев И.А.",
      "place" : "001в",
      "isChanged" : true
    } ]
  }, {
    "targetGroup" : "22СА-2",
    "isAbsolute" : true,
    "changesDate" : 1696230000000,
    "changedLessons" : [ {
      "number" : 0,
      "name" : "ЭВМ",
      "teacher" : "Гарипова Р.М.",
      "place" : "329",
      "isChanged" : true
    }, {
      "number" : 3,
      "name" : "нет",
      "teacher" : "",
      "place" : "",
      "isChanged" : true
    } ]
  }, {
    "targetGroup" : "21СА-2",
    "isAbsolute" : true,
    "changesDate" : 1696230000000,
    "changedLessons" : [ {
      "number" : 3,
      "name" : "нет",
      "teacher" : "",
      "place" : "",
      "isChanged" : true
    } ]
  }, {
    "targetGroup" : "20СА-1",
    "isAbsolute" : true,
    "changesDate" : 1696230000000,
    "changedLessons" : [ {
      "number" : 0,
      "name" : "нет",
      "teacher" : "",
      "place" : "",
      "isChanged" : true
    }, {
      "number" : 4,
      "name" : "Ин яз",
      "teacher" : "Пустовалова Э.У.",
      "place" : "331",
      "isChanged" : true
    } ]
  }, {
    "targetGroup" : "23ПО-1",
    "isAbsolute" : true,
    "changesDate" : 1696230000000,
    "changedLessons" : [ {
      "number" : 0,
      "name" : "нет",
      "teacher" : "",
      "place" : "",
      "isChanged" : true
    }, {
      "number" : 4,
      "name" : "Информатика",
      "teacher" : "Габитова И.А.",
      "place" : "223",
      "isChanged" : true
    } ]
  }, {
    "targetGroup" : "23ПО-2",
    "isAbsolute" : true,
    "changesDate" : 1696230000000,
    "changedLessons" : [ {
      "number" : 0,
      "name" : "Информатика",
      "teacher" : "Габитова И.А.",
      "place" : "223",
      "isChanged" : true
    } ]
  }, {
    "targetGroup" : "23ПО-3",
    "isAbsolute" : true,
    "changesDate" : 1696230000000,
    "changedLessons" : [ {
      "number" : 5,
      "name" : "Общество",
      "teacher" : "Ахметшина Е. В.",
      "place" : "ч/з",
      "isChanged" : true
    } ]
  }, {
    "targetGroup" : "23ПО-5",
    "isAbsolute" : true,
    "changesDate" : 1696230000000,
    "changedLessons" : [ {
      "number" : 3,
      "name" : "Баш я",
      "teacher" : "Юмагулова Г.К.",
      "place" : "312",
      "isChanged" : true
    }, {
      "number" : 4,
      "name" : "Математика",
      "teacher" : "Тяпкина Н.Б.",
      "place" : "11",
      "isChanged" : true
    }, {
      "number" : 5,
      "name" : "Информатика",
      "teacher" : "Габитова И.А.",
      "place" : "223",
      "isChanged" : true
    } ]
  }, {
    "targetGroup" : "23ПО-4",
    "isAbsolute" : true,
    "changesDate" : 1696230000000,
    "changedLessons" : [ {
      "number" : 1,
      "name" : "Лит-ра",
      "teacher" : "Кинзина А. З.",
      "place" : "305",
      "isChanged" : true
    }, {
      "number" : 2,
      "name" : "Русс. Яз.",
      "teacher" : "Кинзина А. З.",
      "place" : "305",
      "isChanged" : true
    }, {
      "number" : 3,
      "name" : "Математика",
      "teacher" : "Гладкова А.Ф.",
      "place" : "325",
      "isChanged" : true
    } ]
  }, {
    "targetGroup" : "22ПО-1",
    "isAbsolute" : true,
    "changesDate" : 1696230000000,
    "changedLessons" : [ {
      "number" : 3,
      "name" : "ТГП",
      "teacher" : "Семенов С. А.",
      "place" : "117",
      "isChanged" : true
    } ]
  }, {
    "targetGroup" : "22ПО-2",
    "isAbsolute" : true,
    "changesDate" : 1696230000000,
    "changedLessons" : [ {
      "number" : 2,
      "name" : "ТГП",
      "teacher" : "Семенов С. А.",
      "place" : "117",
      "isChanged" : true
    } ]
  }, {
    "targetGroup" : "22ПО-3",
    "isAbsolute" : true,
    "changesDate" : 1696230000000,
    "changedLessons" : [ {
      "number" : 1,
      "name" : "ТГП",
      "teacher" : "Семенов С. А.",
      "place" : "117",
      "isChanged" : true
    } ]
  }, {
    "targetGroup" : "23ПД-1",
    "isAbsolute" : true,
    "changesDate" : 1696230000000,
    "changedLessons" : [ {
      "number" : 2,
      "name" : "Общество",
      "teacher" : "Анастасьев А.Г.",
      "place" : "309",
      "isChanged" : true
    }, {
      "number" : 3,
      "name" : "Информатика",
      "teacher" : "Габитова А.И.",
      "place" : "223",
      "isChanged" : true
    }, {
      "number" : 4,
      "name" : "Физика",
      "teacher" : "Кашапов В.В.",
      "place" : "14",
      "isChanged" : true
    }, {
      "number" : 5,
      "name" : "Математика",
      "teacher" : "Лахмуткина Т.Г.",
      "place" : "218",
      "isChanged" : true
    } ]
  }, {
    "targetGroup" : "23ПД-2",
    "isAbsolute" : true,
    "changesDate" : 1696230000000,
    "changedLessons" : [ {
      "number" : 1,
      "name" : "Информатика",
      "teacher" : "Габитова А.И.",
      "place" : "223",
      "isChanged" : true
    }, {
      "number" : 2,
      "name" : "Информатика",
      "teacher" : "Габитова А.И.",
      "place" : "223",
      "isChanged" : true
    }, {
      "number" : 3,
      "name" : "Математика",
      "teacher" : "Лахмуткина Т.Г.",
      "place" : "218",
      "isChanged" : true
    }, {
      "number" : 4,
      "name" : "Математика",
      "teacher" : "Лахмуткина Т.Г.",
      "place" : "218",
      "isChanged" : true
    } ]
  }, {
    "targetGroup" : "22ПСА-3",
    "isAbsolute" : true,
    "changesDate" : 1696230000000,
    "changedLessons" : [ {
      "number" : 2,
      "name" : "БЖД",
      "teacher" : "Драгомиров М.С.",
      "place" : "111а",
      "isChanged" : true
    }, {
      "number" : 3,
      "name" : "История",
      "teacher" : "Исмагилова Г.М.",
      "place" : "315",
      "isChanged" : true
    } ]
  }, {
    "targetGroup" : "21ПО-1",
    "isAbsolute" : true,
    "changesDate" : 1696230000000,
    "changedLessons" : [ {
      "number" : 1,
      "name" : "Угол. процесс",
      "teacher" : "Языкбаев А.Г.",
      "place" : "110",
      "isChanged" : true
    }, {
      "number" : 2,
      "name" : "Угол. процесс",
      "teacher" : "Языкбаев А.Г.",
      "place" : "110",
      "isChanged" : true
    }, {
      "number" : 3,
      "name" : "ПСО",
      "teacher" : "Кильсенбаев Э.Р.",
      "place" : "114",
      "isChanged" : true
    } ]
  }, {
    "targetGroup" : "21ПО-2",
    "isAbsolute" : true,
    "changesDate" : 1696230000000,
    "changedLessons" : [ {
      "number" : 1,
      "name" : "УП 1.01",
      "teacher" : "Хамидова Д.С.",
      "place" : "323",
      "isChanged" : true
    }, {
      "number" : 2,
      "name" : "УП 1.01",
      "teacher" : "Хамидова Д.С.",
      "place" : "323",
      "isChanged" : true
    }, {
      "number" : 3,
      "name" : "ПСО",
      "teacher" : "Кильсенбаев Э.Р.",
      "place" : "114",
      "isChanged" : true
    } ]
  }, {
    "targetGroup" : "21ПО-3",
    "isAbsolute" : true,
    "changesDate" : 1696230000000,
    "changedLessons" : [ {
      "number" : 2,
      "name" : "Физ-ра",
      "teacher" : "Гильманов Р.А.",
      "place" : "",
      "isChanged" : true
    }, {
      "number" : 3,
      "name" : "УП 01.01",
      "teacher" : "Хамидова Д.С.",
      "place" : "323",
      "isChanged" : true
    }, {
      "number" : 4,
      "name" : "УП",
      "teacher" : "Дуйсенов И.А.",
      "place" : "343",
      "isChanged" : true
    }, {
      "number" : 5,
      "name" : "УП",
      "teacher" : "Дуйсенов И.А.",
      "place" : "343",
      "isChanged" : true
    } ]
  }, {
    "targetGroup" : "21ПО-4",
    "isAbsolute" : true,
    "changesDate" : 1696230000000,
    "changedLessons" : [ {
      "number" : 0,
      "name" : "ПСО",
      "teacher" : "Кильсенбаев Э.Р.",
      "place" : "114",
      "isChanged" : true
    }, {
      "number" : 1,
      "name" : "ПСО",
      "teacher" : "Кильсенбаев Э.Р.",
      "place" : "114",
      "isChanged" : true
    }, {
      "number" : 2,
      "name" : "УП 01.01",
      "teacher" : "Хамидова Д.С.",
      "place" : "323",
      "isChanged" : true
    }, {
      "number" : 3,
      "name" : "УП",
      "teacher" : "Дуйсенов И.А.",
      "place" : "343",
      "isChanged" : true
    } ]
  }, {
    "targetGroup" : "23Э-2",
    "isAbsolute" : true,
    "changesDate" : 1696230000000,
    "changedLessons" : [ {
      "number" : 1,
      "name" : "нет",
      "teacher" : "",
      "place" : "",
      "isChanged" : true
    }, {
      "number" : 3,
      "name" : "Общество",
      "teacher" : "Анастасьев А.Г.",
      "place" : "309",
      "isChanged" : true
    } ]
  }, {
    "targetGroup" : "23Л-1",
    "isAbsolute" : true,
    "changesDate" : 1696230000000,
    "changedLessons" : [ {
      "number" : 2,
      "name" : "нет",
      "teacher" : "",
      "place" : "",
      "isChanged" : true
    } ]
  }, {
    "targetGroup" : "23ЗИО-2",
    "isAbsolute" : true,
    "changesDate" : 1696230000000,
    "changedLessons" : [ {
      "number" : 0,
      "name" : "нет",
      "teacher" : "",
      "place" : "",
      "isChanged" : true
    }, {
      "number" : 3,
      "name" : "Математика",
      "teacher" : "Султанов Д. Ф.",
      "place" : "314",
      "isChanged" : true
    }, {
      "number" : 4,
      "name" : "Баш яз",
      "teacher" : "Юмагулова Г.К.",
      "place" : "312",
      "isChanged" : true
    } ]
  }, {
    "targetGroup" : "23УЛ-1",
    "isAbsolute" : true,
    "changesDate" : 1696230000000,
    "changedLessons" : [ {
      "number" : 0,
      "name" : "ИТ В ПД",
      "teacher" : "Уразаева А.А.",
      "place" : "227",
      "isChanged" : true
    }, {
      "number" : 1,
      "name" : "Физ-ра",
      "teacher" : "Емельянова Л.Г.",
      "place" : "",
      "isChanged" : true
    }, {
      "number" : 2,
      "name" : "Ин яз",
      "teacher" : "Пустовалова Э.У.",
      "place" : "2",
      "isChanged" : true
    } ]
  }, {
    "targetGroup" : "22Л-2",
    "isAbsolute" : true,
    "changesDate" : 1696230000000,
    "changedLessons" : [ {
      "number" : 4,
      "name" : "Математика",
      "teacher" : "Гладкова А.Ф.",
      "place" : "325",
      "isChanged" : true
    }, {
      "number" : 5,
      "name" : "Математика",
      "teacher" : "Гладкова А.Ф.",
      "place" : "325",
      "isChanged" : true
    } ]
  }, {
    "targetGroup" : "22Э-2",
    "isAbsolute" : true,
    "changesDate" : 1696230000000,
    "changedLessons" : [ {
      "number" : 2,
      "name" : "Математика",
      "teacher" : "Гладкова А.Ф.",
      "place" : "325",
      "isChanged" : true
    }, {
      "number" : 3,
      "name" : "БЖД",
      "teacher" : "Драгомиров М.С.",
      "place" : "111а",
      "isChanged" : true
    }, {
      "number" : 4,
      "name" : "Основы БУ",
      "teacher" : "Кузнецова Л.Р.",
      "place" : "317",
      "isChanged" : true
    } ]
  }, {
    "targetGroup" : "22Л-1",
    "isAbsolute" : true,
    "changesDate" : 1696230000000,
    "changedLessons" : [ {
      "number" : 0,
      "name" : "Математика",
      "teacher" : "Гладкова А.Ф.",
      "place" : "325",
      "isChanged" : true
    }, {
      "number" : 1,
      "name" : "Математика",
      "teacher" : "Гладкова А.Ф.",
      "place" : "325",
      "isChanged" : true
    } ]
  } ],
  "changesDate" : 1696230000000
}